LICENSE
README.md
setup.py
pyspark_kernel/__init__.py
pyspark_kernel/__main__.py
pyspark_kernel/pyspark_kernel.py
pyspark_kernel/pyspark_magic.py
pyspark_kernel.egg-info/PKG-INFO
pyspark_kernel.egg-info/SOURCES.txt
pyspark_kernel.egg-info/dependency_links.txt
pyspark_kernel.egg-info/requires.txt
pyspark_kernel.egg-info/top_level.txt