Metadata-Version: 1.1
Name: pyspark-kernel
Version: 0.3.0
Summary: A PySpark kernel for Jupyter/IPython
Home-page: https://gitlab.com/teia_engineering/pyspark_kernel
Author: David Fernandez
Author-email: teia.eng.14@gmail.com
License: UNKNOWN
Platform: UNKNOWN
Classifier: Framework :: IPython
Classifier: License :: OSI Approved :: BSD License
Classifier: Programming Language :: Python :: 3
Classifier: Programming Language :: Python :: 2
Classifier: Topic :: System :: Shells
